{
  "response_code": 0,
  "results": [
    {
      "category": "Science: Gadgets",
      "type": "multiple",
      "difficulty": "medium",
      "question": "What are the base station trackers used for the HTC Vive called?",
      "correct_answer": "Lighthouse",
      "incorrect_answers": [
        "Motion",
        "Constellation ",
        "Trackers"
      ]
    },
    {
      "category": "Science: Gadgets",
      "type": "multiple",
      "difficulty": "medium",
      "question": "Which company designed the 'Betamax' video cassette format?",
      "correct_answer": "Sony",
      "incorrect_answers": [
        "Panasonic",
        "LG",
        "Fujitsu"
      ]
    },
    {
      "category": "Science: Gadgets",
      "type": "multiple",
      "difficulty": "hard",
      "question": "Which of the following is the standard THX subwoofer crossover frequency?",
      "correct_answer": "80 Hz",
      "incorrect_answers": [
        "70 Hz",
        "90 Hz",
        "100 Hz"
      ]
    },
    {
      "category": "Science: Gadgets",
      "type": "multiple",
      "difficulty": "medium",
      "question": "Who patented a steam engine that produced continuous rotary motion?",
      "correct_answer": "James Watt",
      "incorrect_answers": [
        "Nikola Tesla",
        "Albert Einstein",
        "Alessandro Volta"
      ]
    },
    {
      "category": "Science: Gadgets",
      "type": "multiple",
      "difficulty": "easy",
      "question": "When was the Tamagotchi digital pet released?",
      "correct_answer": "1996",
      "incorrect_answers": [
        "1989",
        "1992",
        "1990"
      ]
    },
    {
      "category": "Science: Gadgets",
      "type": "multiple",
      "difficulty": "medium",
      "question": "In what year was the Oculus Rift revealed to the public through a Kickstarter campaign?",
      "correct_answer": "2012",
      "incorrect_answers": [
        "2010",
        "2011",
        "2013"
      ]
    },
    {
      "category": "Science: Gadgets",
      "type": "multiple",
      "difficulty": "medium",
      "question": "Which company developed the Hololens?",
      "correct_answer": "Microsoft",
      "incorrect_answers": [
        "HTC",
        "Oculus",
        "Tobii"
      ]
    },
    {
      "category": "Science: Gadgets",
      "type": "multiple",
      "difficulty": "hard",
      "question": "Which of the following cellular device companies is NOT headquartered in Asia?",
      "correct_answer": "Nokia",
      "incorrect_answers": [
        "LG Electronics",
        "Samsung",
        "HTC"
      ]
    },
    {
      "category": "Science: Gadgets",
      "type": "multiple",
      "difficulty": "medium",
      "question": "What is the 'Mitsubishi Wakamaru'?",
      "correct_answer": "A robot",
      "incorrect_answers": [
        "A pickup truck",
        "An motorcycle",
        "A motorboat"
      ]
    },
    {
      "category": "Science: Gadgets",
      "type": "multiple",
      "difficulty": "medium",
      "question": "What is the most significant side venture the popular firearms company, Remington, has pursued?",
      "correct_answer": "Typewriters",
      "incorrect_answers": [
        "Blenders",
        "Ceiling Fans",
        "Door Knobs"
      ]
    }
  ]
}